Metadata-Version: 1.1
Name: BT-Manager
Version: 0.3.0
Summary: Python-based Bluetooth Device Management
Home-page: https://github.com/liamw9534/bt-manager
Author: Liam Wickins
Author-email: liamw9534@gmail.com
License: Apache License, Version 2.0
Platform: UNKNOWN
Classifier: Development Status :: 3 - Alpha
Classifier: Intended Audience :: End Users/Desktop
Classifier: License :: OSI Approved :: Apache Software License
Classifier: Operating System :: POSIX :: Linux
Classifier: Programming Language :: Python :: 2
Classifier: Programming Language :: Python :: 2.7
Classifier: Topic :: Software Development :: Libraries
Classifier: Topic :: Communications
